pdex/__init__.py
pdex/_parallel.py
pdex/_pseudobulk.py
pdex/_single_cell.py
pdex/_utils.py
pdex/py.typed
pdex-0.1.28.dist-info/METADATA
pdex-0.1.28.dist-info/WHEEL
pdex-0.1.28.dist-info/licenses/LICENSE
pdex-0.1.28.dist-info/RECORD
