Metadata-Version: 2.4
Name: pdex
Version: 0.1.28
Summary: Parallel differential expression for single-cell perturbation sequencing
Author-email: noam teyssier <noam.teyssier@arcinstitute.org>
License-File: LICENSE
Requires-Python: >=3.10
Requires-Dist: adpbulk>=0.1.4
Requires-Dist: anndata>=0.9.0
Requires-Dist: numba>=0.61.2
Requires-Dist: numpy>=1.0.0
Requires-Dist: pandas>=2.0.0
Requires-Dist: polars>=1.30.0
Requires-Dist: pyarrow>=18.0.0
Requires-Dist: pydeseq2>=0.5.1
Requires-Dist: scipy>=1.15.2
Requires-Dist: tqdm>=4.67.1
